Workbook

Sheet 模型说明
A1: 中银E贷 + 香港港币基金三阶段策略模型（v3）
A3: 模型结构 | B3: 默认24个月可新增贷款，主策略期为36个月，另延伸12个月追踪用户手动改变策略后可能产生的期后贷款到期。
A5: 策略一 | B5: 默认第1至12个月：每月新增23,400元人民币贷款用于大陆消费，同时将等值港币投入基金。
A6: 策略二 | B6: 默认第13至24个月：每月新增23,400元贷款，直接用于偿还12个月前对应贷款本金，不再购买基金。
A7: 策略三 | B7: 默认第25至36个月：不新增贷款，优先使用内部现金池，再卖出基金偿还当月本金及利息，默认不动用外部资金池。
A8: 期后规则 | B8: 第37至48个月不提供新策略选择。如前36个月手动改动策略后仍有贷款未清偿，当月分红先进入内部现金池，随后内部现金池优先还款，不足部分直接计入外部资金池。
A10: 内部现金池 | B10: 记录累计现金账户余额。每月收到基金分红后，用于支付扣除新贷款资金后的贷款还款；策略三还款不足部分再卖基金。内部现金池不允许为负。
A11: 外部资金池 | B11: 记录模型计划之外的净资金投入。默认三阶段下第三年通过内部现金池和基金赎回还款，因此外部资金池第三年合计应为零；用户更改策略导致缺口或期后未偿款项时，缺口自动计入外部资金池。
A13: 操作方法 | B13: 在“月度资金流”B列使用下拉菜单选择每月策略。默认第1年策略一、第2年策略二、第3年策略三。黄色/蓝字为可修改输入。
A15: 风险提示 | B15: 本模型仅作情景分析，不构成投资或借贷建议。实际基金净值、赎回到账时间、贷款审批、提前还款规则、利率与汇率均可能改变结果。

Sheet 参数设置
A1: 参数设置
A3: 基础假设
A4: 模型开始日 | B4: 46244 | C4: 首笔贷款及基金申购日
A5: 每月人民币标准金额 | B5: 23400 | C5: 策略一/二的标准新增贷款额
A6: 连续贷款月数上限 | B6: 24 | C6: 默认可新增贷款24个月；策略选择仍可在前36个月调整
A7: 汇率基准（人民币/港币） | B7: 0.86 | C7: 1港币兑换人民币
A8: 主策略期（月） | B8: 36 | C8: 三阶段合计期限
A9: 延伸追踪期（月） | B9: 12 | C9: 追踪手动改策略产生的期后贷款
A11: 中银E贷假设
A12: 年利率 | B12: 0.033 | C12: 根据用户的中银E贷试算
A13: 计息年基数 | B13: 360 | C13: Actual/360
A14: 贷款期限（月） | B14: 12 | C14: 每笔贷款期限
A15: 每月结息日 | B15: 5 | C15: 首个结息日按放款后第二个月
A16: 每期金额取整位数 | B16: 2 | C16: 人民币分
A18: 港币基金假设
A19: 预计年化分红率 | B19: 0.15 | C19: 现金分红率，非保证
A20: 每年分红次数 | B20: 12 | C20: 按月分红
A21: 每月除息日 | B21: 28 | C21: 当月申购假设可参与当月除息
A22: 分红发放日 | B22: 8 | C22: 次月发放
A23: 申购费用率 | B23: 0.001 | C23: 申购时扣除
A24: 赎回费用率 | B24: 0.001 | C24: 卖出基金时扣除

Sheet 月度资金流
A1: 月度资金流与三阶段策略控制
A3: 累计外部资金池投入 | E3: 内部现金池期末 | I3: 基金本金期末 | M3: 累计贷款利息 | Q3: 策略期末净资产 | U3: 第三年外部资金合计
A4: =SUM(T7:T54) -> 0 | E4: =U54 -> 13476.886 | I4: =V54 -> 87713.493 | M4: =SUM(L7:L54) -> 18816.84 | Q4: =Z54 -> 101190.38 | U4: =SUM(T31:T42) -> 0
A6: 月份 | B6: 当月策略（下拉） | C6: 当月新增贷款（人民币） | D6: 汇率（人民币/港币） | E6: 策略一港币投入 | F6: 基金申购费用 | G6: 基金净申购 | H6: 期初基金本金 | I6: 当月应计分红 | J6: 收到分红 | K6: 当月应还本金（人民币） | L6: 当月应还利息（人民币） | M6: 还款折港币 | N6: 新贷款用于还本（港币） | O6: 内部现金池期初 | P6: 分红后内部池 | Q6: 内部池用于还款 | R6: 基金赎回净额 | S6: 基金赎回毛额 | T6: 外部资金池投入 | U6: 内部现金池期末 | V6: 期末基金本金 | W6: 期末未偿贷款（人民币） | X6: 负债折港币 | Y6: 基金资产+内部池 | Z6: 策略净资产 | AA6: 资金来源校验
A7: =EDATE(DATE(YEAR(参数设置!$B$4),MONTH(参数设置!$B$4),1),ROW()-7) -> 46235 | B7: 策略一：消费贷款+买基金 | C7: =IF(AND(ROW()-6<=参数设置!$B$6,OR(B7=策略字典!$A$1,B7=策略字典!$A$2)),参数设置!$B$5,0) -> 23400 | D7: =参数设置!$B$7 -> 0.86 | E7: =IF(B7=策略字典!$A$1,C7/D7,0) -> 27209.302 | F7: =E7*参数设置!$B$23 -> 27.209302 | G7: =E7-F7 -> 27182.093 | H7: =IF(ROW()=7,0,V6) -> 0 | I7: =(H7+G7)*参数设置!$B$19/参数设置!$B$20 -> 339.77616 | J7: =IF(ROW()=7,0,I6) -> 0 | K7: =SUMIFS(贷款明细!$I$4:$I$435,贷款明细!$G$4:$G$435,">="&A7,贷款明细!$G$4:$G$435,"<"&EDATE(A7,1)) -> 0 | L7: =SUMIFS(贷款明细!$J$4:$J$435,贷款明细!$G$4:$G$435,">="&A7,贷款明细!$G$4:$G$435,"<"&EDATE(A7,1)) -> 0 | M7: =(K7+L7)/D7 -> 0 | N7: =IF(B7=策略字典!$A$2,MIN(C7,K7)/D7,0) -> 0 | O7: =IF(ROW()=7,0,U6) -> 0 | P7: =O7+J7 -> 0 | Q7: =MIN(P7,MAX(0,M7-N7)) -> 0 | R7: =IF(B7=策略字典!$A$3,MIN(H7+G7,MAX(0,M7-N7-Q7)),0) -> 0 | S7: =IF(R7=0,0,R7/(1-参数设置!$B$24)) -> 0 | T7: =MAX(0,M7-N7-Q7-R7) -> 0 | U7: =P7-Q7 -> 0 | V7: =MAX(0,H7+G7-S7) -> 27182.093 | W7: =SUM($C$7:C7)-SUM($K$7:K7) -> 23400 | X7: =W7/D7 -> 27209.302 | Y7: =V7+U7 -> 27182.093 | Z7: =Y7-X7 -> -27.209302 | AA7: =N7+Q7+R7+T7-M7 -> 0
A8: =EDATE(DATE(YEAR(参数设置!$B$4),MONTH(参数设置!$B$4),1),ROW()-7) -> 46266 | B8: 策略一：消费贷款+买基金 | C8: =IF(AND(ROW()-6<=参数设置!$B$6,OR(B8=策略字典!$A$1,B8=策略字典!$A$2)),参数设置!$B$5,0) -> 23400 | D8: =参数设置!$B$7 -> 0.86 | E8: =IF(B8=策略字典!$A$1,C8/D8,0) -> 27209.302 | F8: =E8*参数设置!$B$23 -> 27.209302 | G8: =E8-F8 -> 27182.093 | H8: =IF(ROW()=7,0,V7) -> 27182.093 | I8: =(H8+G8)*参数设置!$B$19/参数设置!$B$20 -> 679.55233 | J8: =IF(ROW()=7,0,I7) -> 339.77616 | K8: =SUMIFS(贷款明细!$I$4:$I$435,贷款明细!$G$4:$G$435,">="&A8,贷款明细!$G$4:$G$435,"<"&EDATE(A8,1)) -> 0 | L8: =SUMIFS(贷款明细!$J$4:$J$435,贷款明细!$G$4:$G$435,">="&A8,贷款明细!$G$4:$G$435,"<"&EDATE(A8,1)) -> 0 | M8: =(K8+L8)/D8 -> 0 | N8: =IF(B8=策略字典!$A$2,MIN(C8,K8)/D8,0) -> 0 | O8: =IF(ROW()=7,0,U7) -> 0 | P8: =O8+J8 -> 339.77616 | Q8: =MIN(P8,MAX(0,M8-N8)) -> 0 | R8: =IF(B8=策略字典!$A$3,MIN(H8+G8,MAX(0,M8-N8-Q8)),0) -> 0 | S8: =IF(R8=0,0,R8/(1-参数设置!$B$24)) -> 0 | T8: =MAX(0,M8-N8-Q8-R8) -> 0 | U8: =P8-Q8 -> 339.77616 | V8: =MAX(0,H8+G8-S8) -> 54364.186 | W8: =SUM($C$7:C8)-SUM($K$7:K8) -> 46800 | X8: =W8/D8 -> 54418.605 | Y8: =V8+U8 -> 54703.962 | Z8: =Y8-X8 -> 285.35756 | AA8: =N8+Q8+R8+T8-M8 -> 0
A9: =EDATE(DATE(YEAR(参数设置!$B$4),MONTH(参数设置!$B$4),1),ROW()-7) -> 46296 | B9: 策略一：消费贷款+买基金 | C9: =IF(AND(ROW()-6<=参数设置!$B$6,OR(B9=策略字典!$A$1,B9=策略字典!$A$2)),参数设置!$B$5,0) -> 23400 | D9: =参数设置!$B$7 -> 0.86 | E9: =IF(B9=策略字典!$A$1,C9/D9,0) -> 27209.302 | F9: =E9*参数设置!$B$23 -> 27.209302 | G9: =E9-F9 -> 27182.093 | H9: =IF(ROW()=7,0,V8) -> 54364.186 | I9: =(H9+G9)*参数设置!$B$19/参数设置!$B$20 -> 1019.3285 | J9: =IF(ROW()=7,0,I8) -> 679.55233 | K9: =SUMIFS(贷款明细!$I$4:$I$435,贷款明细!$G$4:$G$435,">="&A9,贷款明细!$G$4:$G$435,"<"&EDATE(A9,1)) -> 0 | L9: =SUMIFS(贷款明细!$J$4:$J$435,贷款明细!$G$4:$G$435,">="&A9,贷款明细!$G$4:$G$435,"<"&EDATE(A9,1)) -> 120.12 | M9: =(K9+L9)/D9 -> 139.67442 | N9: =IF(B9=策略字典!$A$2,MIN(C9,K9)/D9,0) -> 0 | O9: =IF(ROW()=7,0,U8) -> 339.77616 | P9: =O9+J9 -> 1019.3285 | Q9: =MIN(P9,MAX(0,M9-N9)) -> 139.67442 | R9: =IF(B9=策略字典!$A$3,MIN(H9+G9,MAX(0,M9-N9-Q9)),0) -> 0 | S9: =IF(R9=0,0,R9/(1-参数设置!$B$24)) -> 0 | T9: =MAX(0,M9-N9-Q9-R9) -> 0 | U9: =P9-Q9 -> 879.65407 | V9: =MAX(0,H9+G9-S9) -> 81546.279 | W9: =SUM($C$7:C9)-SUM($K$7:K9) -> 70200 | X9: =W9/D9 -> 81627.907 | Y9: =V9+U9 -> 82425.933 | Z9: =Y9-X9 -> 798.02616 | AA9: =N9+Q9+R9+T9-M9 -> 0
A10: =EDATE(DATE(YEAR(参数设置!$B$4),MONTH(参数设置!$B$4),1),ROW()-7) -> 46327 | B10: 策略一：消费贷款+买基金 | C10: =IF(AND(ROW()-6<=参数设置!$B$6,OR(B10=策略字典!$A$1,B10=策略字典!$A$2)),参数设置!$B$5,0) -> 23400 | D10: =参数设置!$B$7 -> 0.86 | E10: =IF(B10=策略字典!$A$1,C10/D10,0) -> 27209.302 | F10: =E10*参数设置!$B$23 -> 27.209302 | G10: =E10-F10 -> 27182.093 | H10: =IF(ROW()=7,0,V9) -> 81546.279 | I10: =(H10+G10)*参数设置!$B$19/参数设置!$B$20 -> 1359.1047 | J10: =IF(ROW()=7,0,I9) -> 1019.3285 | K10: =SUMIFS(贷款明细!$I$4:$I$435,贷款明细!$G$4:$G$435,">="&A10,贷款明细!$G$4:$G$435,"<"&EDATE(A10,1)) -> 0 | L10: =SUMIFS(贷款明细!$J$4:$J$435,贷款明细!$G$4:$G$435,">="&A10,贷款明细!$G$4:$G$435,"<"&EDATE(A10,1)) -> 186.62 | M10: =(K10+L10)/D10 -> 217 | N10: =IF(B10=策略字典!$A$2,MIN(C10,K10)/D10,0) -> 0 | O10: =IF(ROW()=7,0,U9) -> 879.65407 | P10: =O10+J10 -> 1898.9826 | Q10: =MIN(P10,MAX(0,M10-N10)) -> 217 | R10: =IF(B10=策略字典!$A$3,MIN(H10+G10,MAX(0,M10-N10-Q10)),0) -> 0 | S10: =IF(R10=0,0,R10/(1-参数设置!$B$24)) -> 0 | T10: =MAX(0,M10-N10-Q10-R10) -> 0 | U10: =P10-Q10 -> 1681.9826 | V10: =MAX(0,H10+G10-S10) -> 108728.37 | W10: =SUM($C$7:C10)-SUM($K$7:K10) -> 93600 | X10: =W10/D10 -> 108837.21 | Y10: =V10+U10 -> 110410.35 | Z10: =Y10-X10 -> 1573.1453 | AA10: =N10+Q10+R10+T10-M10 -> 0
A11: =EDATE(DATE(YEAR(参数设置!$B$4),MONTH(参数设置!$B$4),1),ROW()-7) -> 46357 | B11: 策略一：消费贷款+买基金 | C11: =IF(AND(ROW()-6<=参数设置!$B$6,OR(B11=策略字典!$A$1,B11=策略字典!$A$2)),参数设置!$B$5,0) -> 23400 | D11: =参数设置!$B$7 -> 0.86 | E11: =IF(B11=策略字典!$A$1,C11/D11,0) -> 27209.302 | F11: =E11*参数设置!$B$23 -> 27.209302 | G11: =E11-F11 -> 27182.093 | H11: =IF(ROW()=7,0,V10) -> 108728.37 | I11: =(H11+G11)*参数设置!$B$19/参数设置!$B$20 -> 1698.8808 | J11: =IF(ROW()=7,0,I10) -> 1359.1047 | K11: =SUMIFS(贷款明细!$I$4:$I$435,贷款明细!$G$4:$G$435,">="&A11,贷款明细!$G$4:$G$435,"<"&EDATE(A11,1)) -> 0 | L11: =SUMIFS(贷款明细!$J$4:$J$435,贷款明细!$G$4:$G$435,">="&A11,贷款明细!$G$4:$G$435,"<"&EDATE(A11,1)) -> 248.82 | M11: =(K11+L11)/D11 -> 289.32558 | N11: =IF(B11=策略字典!$A$2,MIN(C11,K11)/D11,0) -> 0 | O11: =IF(ROW()=7,0,U10) -> 1681.9826 | P11: =O11+J11 -> 3041.0872 | Q11: =MIN(P11,MAX(0,M11-N11)) -> 289.32558 | R11: =IF(B11=策略字典!$A$3,MIN(H11+G11,MAX(0,M11-N11-Q11)),0) -> 0 | S11: =IF(R11=0,0,R11/(1-参数设置!$B$24)) -> 0 | T11: =MAX(0,M11-N11-Q11-R11) -> 0 | U11: =P11-Q11 -> 2751.7616 | V11: =MAX(0,H11+G11-S11) -> 135910.47 | W11: =SUM($C$7:C11)-SUM($K$7:K11) -> 117000 | X11: =W11/D11 -> 136046.51 | Y11: =V11+U11 -> 138662.23 | Z11: =Y11-X11 -> 2615.7151 | AA11: =N11+Q11+R11+T11-M11 -> 0
A12: =EDATE(DATE(YEAR(参数设置!$B$4),MONTH(参数设置!$B$4),1),ROW()-7) -> 46388 | B12: 策略一：消费贷款+买基金 | C12: =IF(AND(ROW()-6<=参数设置!$B$6,OR(B12=策略字典!$A$1,B12=策略字典!$A$2)),参数设置!$B$5,0) -> 23400 | D12: =参数设置!$B$7 -> 0.86 | E12: =IF(B12=策略字典!$A$1,C12/D12,0) -> 27209.302 | F12: =E12*参数设置!$B$23 -> 27.209302 | G12: =E12-F12 -> 27182.093 | H12: =IF(ROW()=7,0,V11) -> 135910.47 | I12: =(H12+G12)*参数设置!$B$19/参数设置!$B$20 -> 2038.657 | J12: =IF(ROW()=7,0,I11) -> 1698.8808 | K12: =SUMIFS(贷款明细!$I$4:$I$435,贷款明细!$G$4:$G$435,">="&A12,贷款明细!$G$4:$G$435,"<"&EDATE(A12,1)) -> 0 | L12: =SUMIFS(贷款明细!$J$4:$J$435,贷款明细!$G$4:$G$435,">="&A12,贷款明细!$G$4:$G$435,"<"&EDATE(A12,1)) -> 319.62 | M12: =(K12+L12)/D12 -> 371.65116 | N12: =IF(B12=策略字典!$A$2,MIN(C12,K12)/D12,0) -> 0 | O12: =IF(ROW()=7,0,U11) -> 2751.7616 | P12: =O12+J12 -> 4450.6424 | Q12: =MIN(P12,MAX(0,M12-N12)) -> 371.65116 | R12: =IF(B12=策略字典!$A$3,MIN(H12+G12,MAX(0,M12-N12-Q12)),0) -> 0 | S12: =IF(R12=0,0,R12/(1-参数设置!$B$24)) -> 0 | T12: =MAX(0,M12-N12-Q12-R12) -> 0 | U12: =P12-Q12 -> 4078.9913 | V12: =MAX(0,H12+G12-S12) -> 163092.56 | W12: =SUM($C$7:C12)-SUM($K$7:K12) -> 140400 | X12: =W12/D12 -> 163255.81 | Y12: =V12+U12 -> 167171.55 | Z12: =Y12-X12 -> 3915.7355 | AA12: =N12+Q12+R12+T12-M12 -> 0
A13: =EDATE(DATE(YEAR(参数设置!$B$4),MONTH(参数设置!$B$4),1),ROW()-7) -> 46419 | B13: 策略一：消费贷款+买基金 | C13: =IF(AND(ROW()-6<=参数设置!$B$6,OR(B13=策略字典!$A$1,B13=策略字典!$A$2)),参数设置!$B$5,0) -> 23400 | D13: =参数设置!$B$7 -> 0.86 | E13: =IF(B13=策略字典!$A$1,C13/D13,0) -> 27209.302 | F13: =E13*参数设置!$B$23 -> 27.209302 | G13: =E13-F13 -> 27182.093 | H13: =IF(ROW()=7,0,V12) -> 163092.56 | I13: =(H13+G13)*参数设置!$B$19/参数设置!$B$20 -> 2378.4331 | J13: =IF(ROW()=7,0,I12) -> 2038.657 | K13: =SUMIFS(贷款明细!$I$4:$I$435,贷款明细!$G$4:$G$435,">="&A13,贷款明细!$G$4:$G$435,"<"&EDATE(A13,1)) -> 0 | L13: =SUMIFS(贷款明细!$J$4:$J$435,贷款明细!$G$4:$G$435,">="&A13,贷款明细!$G$4:$G$435,"<"&EDATE(A13,1)) -> 388.27 | M13: =(K13+L13)/D13 -> 451.47674 | N13: =IF(B13=策略字典!$A$2,MIN(C13,K13)/D13,0) -> 0 | O13: =IF(ROW()=7,0,U12) -> 4078.9913 | P13: =O13+J13 -> 6117.6483 | Q13: =MIN(P13,MAX(0,M13-N13)) -> 451.47674 | R13: =IF(B13=策略字典!$A$3,MIN(H13+G13,MAX(0,M13-N13-Q13)),0) -> 0 | S13: =IF(R13=0,0,R13/(1-参数设置!$B$24)) -> 0 | T13: =MAX(0,M13-N13-Q13-R13) -> 0 | U13: =P13-Q13 -> 5666.1715 | V13: =MAX(0,H13+G13-S13) -> 190274.65 | W13: =SUM($C$7:C13)-SUM($K$7:K13) -> 163800 | X13: =W13/D13 -> 190465.12 | Y13: =V13+U13 -> 195940.82 | Z13: =Y13-X13 -> 5475.7064 | AA13: =N13+Q13+R13+T13-M13 -> 0
A14: =EDATE(DATE(YEAR(参数设置!$B$4),MONTH(参数设置!$B$4),1),ROW()-7) -> 46447 | B14: 策略一：消费贷款+买基金 | C14: =IF(AND(ROW()-6<=参数设置!$B$6,OR(B14=策略字典!$A$1,B14=策略字典!$A$2)),参数设置!$B$5,0) -> 23400 | D14: =参数设置!$B$7 -> 0.86 | E14: =IF(B14=策略字典!$A$1,C14/D14,0) -> 27209.302 | F14: =E14*参数设置!$B$23 -> 27.209302 | G14: =E14-F14 -> 27182.093 | H14: =IF(ROW()=7,0,V13) -> 190274.65 | I14: =(H14+G14)*参数设置!$B$19/参数设置!$B$20 -> 2718.2093 | J14: =IF(ROW()=7,0,I13) -> 2378.4331 | K14: =SUMIFS(贷款明细!$I$4:$I$435,贷款明细!$G$4:$G$435,">="&A14,贷款明细!$G$4:$G$435,"<"&EDATE(A14,1)) -> 0 | L14: =SUMIFS(贷款明细!$J$4:$J$435,贷款明细!$G$4:$G$435,">="&A14,贷款明细!$G$4:$G$435,"<"&EDATE(A14,1)) -> 416.13 | M14: =(K14+L14)/D14 -> 483.87209 | N14: =IF(B14=策略字典!$A$2,MIN(C14,K14)/D14,0) -> 0 | O14: =IF(ROW()=7,0,U13) -> 5666.1715 | P14: =O14+J14 -> 8044.6047 | Q14: =MIN(P14,MAX(0,M14-N14)) -> 483.87209 | R14: =IF(B14=策略字典!$A$3,MIN(H14+G14,MAX(0,M14-N14-Q14)),0) -> 0 | S14: =IF(R14=0,0,R14/(1-参数设置!$B$24)) -> 0 | T14: =MAX(0,M14-N14-Q14-R14) -> 0 | U14: =P14-Q14 -> 7560.7326 | V14: =MAX(0,H14+G14-S14) -> 217456.74 | W14: =SUM($C$7:C14)-SUM($K$7:K14) -> 187200 | X14: =W14/D14 -> 217674.42 | Y14: =V14+U14 -> 225017.48 | Z14: =Y14-X14 -> 7343.0581 | AA14: =N14+Q14+R14+T14-M14 -> 0
A15: =EDATE(DATE(YEAR(参数设置!$B$4),MONTH(参数设置!$B$4),1),ROW()-7) -> 46478 | B15: 策略一：消费贷款+买基金 | C15: =IF(AND(ROW()-6<=参数设置!$B$6,OR(B15=策略字典!$A$1,B15=策略字典!$A$2)),参数设置!$B$5,0) -> 23400 | D15: =参数设置!$B$7 -> 0.86 | E15: =IF(B15=策略字典!$A$1,C15/D15,0) -> 27209.302 | F15: =E15*参数设置!$B$23 -> 27.209302 | G15: =E15-F15 -> 27182.093 | H15: =IF(ROW()=7,0,V14) -> 217456.74 | I15: =(H15+G15)*参数设置!$B$19/参数设置!$B$20 -> 3057.9855 | J15: =IF(ROW()=7,0,I14) -> 2718.2093 | K15: =SUMIFS(贷款明细!$I$4:$I$435,贷款明细!$G$4:$G$435,">="&A15,贷款明细!$G$4:$G$435,"<"&EDATE(A15,1)) -> 0 | L15: =SUMIFS(贷款明细!$J$4:$J$435,贷款明细!$G$4:$G$435,">="&A15,贷款明细!$G$4:$G$435,"<"&EDATE(A15,1)) -> 514.83 | M15: =(K15+L15)/D15 -> 598.63953 | N15: =IF(B15=策略字典!$A$2,MIN(C15,K15)/D15,0) -> 0 | O15: =IF(ROW()=7,0,U14) -> 7560.7326 | P15: =O15+J15 -> 10278.942 | Q15: =MIN(P15,MAX(0,M15-N15)) -> 598.63953 | R15: =IF(B15=策略字典!$A$3,MIN(H15+G15,MAX(0,M15-N15-Q15)),0) -> 0 | S15: =IF(R15=0,0,R15/(1-参数设置!$B$24)) -> 0 | T15: =MAX(0,M15-N15-Q15-R15) -> 0 | U15: =P15-Q15 -> 9680.3023 | V15: =MAX(0,H15+G15-S15) -> 244638.84 | W15: =SUM($C$7:C15)-SUM($K$7:K15) -> 210600 | X15: =W15/D15 -> 244883.72 | Y15: =V15+U15 -> 254319.14 | Z15: =Y15-X15 -> 9435.4186 | AA15: =N15+Q15+R15+T15-M15 -> 0
A16: =EDATE(DATE(YEAR(参数设置!$B$4),MONTH(参数设置!$B$4),1),ROW()-7) -> 46508 | B16: 策略一：消费贷款+买基金 | C16: =IF(AND(ROW()-6<=参数设置!$B$6,OR(B16=策略字典!$A$1,B16=策略字典!$A$2)),参数设置!$B$5,0) -> 23400 | D16: =参数设置!$B$7 -> 0.86 | E16: =IF(B16=策略字典!$A$1,C16/D16,0) -> 27209.302 | F16: =E16*参数设置!$B$23 -> 27.209302 | G16: =E16-F16 -> 27182.093 | H16: =IF(ROW()=7,0,V15) -> 244638.84 | I16: =(H16+G16)*参数设置!$B$19/参数设置!$B$20 -> 3397.7616 | J16: =IF(ROW()=7,0,I15) -> 3057.9855 | K16: =SUMIFS(贷款明细!$I$4:$I$435,贷款明细!$G$4:$G$435,">="&A16,贷款明细!$G$4:$G$435,"<"&EDATE(A16,1)) -> 0 | L16: =SUMIFS(贷款明细!$J$4:$J$435,贷款明细!$G$4:$G$435,">="&A16,贷款明细!$G$4:$G$435,"<"&EDATE(A16,1)) -> 570.57 | M16: =(K16+L16)/D16 -> 663.45349 | N16: =IF(B16=策略字典!$A$2,MIN(C16,K16)/D16,0) -> 0 | O16: =IF(ROW()=7,0,U15) -> 9680.3023 | P16: =O16+J16 -> 12738.288 | Q16: =MIN(P16,MAX(0,M16-N16)) -> 663.45349 | R16: =IF(B16=策略字典!$A$3,MIN(H16+G16,MAX(0,M16-N16-Q16)),0) -> 0 | S16: =IF(R16=0,0,R16/(1-参数设置!$B$24)) -> 0 | T16: =MAX(0,M16-N16-Q16-R16) -> 0 | U16: =P16-Q16 -> 12074.834 | V16: =MAX(0,H16+G16-S16) -> 271820.93 | W16: =SUM($C$7:C16)-SUM($K$7:K16) -> 234000 | X16: =W16/D16 -> 272093.02 | Y16: =V16+U16 -> 283895.76 | Z16: =Y16-X16 -> 11802.741 | AA16: =N16+Q16+R16+T16-M16 -> 0
A17: =EDATE(DATE(YEAR(参数设置!$B$4),MONTH(参数设置!$B$4),1),ROW()-7) -> 46539 | B17: 策略一：消费贷款+买基金 | C17: =IF(AND(ROW()-6<=参数设置!$B$6,OR(B17=策略字典!$A$1,B17=策略字典!$A$2)),参数设置!$B$5,0) -> 23400 | D17: =参数设置!$B$7 -> 0.86 | E17: =IF(B17=策略字典!$A$1,C17/D17,0) -> 27209.302 | F17: =E17*参数设置!$B$23 -> 27.209302 | G17: =E17-F17 -> 27182.093 | H17: =IF(ROW()=7,0,V16) -> 271820.93 | I17: =(H17+G17)*参数设置!$B$19/参数设置!$B$20 -> 3737.5378 | J17: =IF(ROW()=7,0,I16) -> 3397.7616 | K17: =SUMIFS(贷款明细!$I$4:$I$435,贷款明细!$G$4:$G$435,">="&A17,贷款明细!$G$4:$G$435,"<"&EDATE(A17,1)) -> 0 | L17: =SUMIFS(贷款明细!$J$4:$J$435,贷款明细!$G$4:$G$435,">="&A17,贷款明细!$G$4:$G$435,"<"&EDATE(A17,1)) -> 652.12 | M17: =(K17+L17)/D17 -> 758.27907 | N17: =IF(B17=策略字典!$A$2,MIN(C17,K17)/D17,0) -> 0 | O17: =IF(ROW()=7,0,U16) -> 12074.834 | P17: =O17+J17 -> 15472.596 | Q17: =MIN(P17,MAX(0,M17-N17)) -> 758.27907 | R17: =IF(B17=策略字典!$A$3,MIN(H17+G17,MAX(0,M17-N17-Q17)),0) -> 0 | S17: =IF(R17=0,0,R17/(1-参数设置!$B$24)) -> 0 | T17: =MAX(0,M17-N17-Q17-R17) -> 0 | U17: =P17-Q17 -> 14714.317 | V17: =MAX(0,H17+G17-S17) -> 299003.02 | W17: =SUM($C$7:C17)-SUM($K$7:K17) -> 257400 | X17: =W17/D17 -> 299302.33 | Y17: =V17+U17 -> 313717.34 | Z17: =Y17-X17 -> 14415.015 | AA17: =N17+Q17+R17+T17-M17 -> 0
A18: =EDATE(DATE(YEAR(参数设置!$B$4),MONTH(参数设置!$B$4),1),ROW()-7) -> 46569 | B18: 策略一：消费贷款+买基金 | C18: =IF(AND(ROW()-6<=参数设置!$B$6,OR(B18=策略字典!$A$1,B18=策略字典!$A$2)),参数设置!$B$5,0) -> 23400 | D18: =参数设置!$B$7 -> 0.86 | E18: =IF(B18=策略字典!$A$1,C18/D18,0) -> 27209.302 | F18: =E18*参数设置!$B$23 -> 27.209302 | G18: =E18-F18 -> 27182.093 | H18: =IF(ROW()=7,0,V17) -> 299003.02 | I18: =(H18+G18)*参数设置!$B$19/参数设置!$B$20 -> 4077.314 | J18: =IF(ROW()=7,0,I17) -> 3737.5378 | K18: =SUMIFS(贷款明细!$I$4:$I$435,贷款明细!$G$4:$G$435,">="&A18,贷款明细!$G$4:$G$435,"<"&EDATE(A18,1)) -> 0 | L18: =SUMIFS(贷款明细!$J$4:$J$435,贷款明细!$G$4:$G$435,">="&A18,贷款明细!$G$4:$G$435,"<"&EDATE(A18,1)) -> 699.27 | M18: =(K18+L18)/D18 -> 813.10465 | N18: =IF(B18=策略字典!$A$2,MIN(C18,K18)/D18,0) -> 0 | O18: =IF(ROW()=7,0,U17) -> 14714.317 | P18: =O18+J18 -> 18451.855 | Q18: =MIN(P18,MAX(0,M18-N18)) -> 813.10465 | R18: =IF(B18=策略字典!$A$3,MIN(H18+G18,MAX(0,M18-N18-Q18)),0) -> 0 | S18: =IF(R18=0,0,R18/(1-参数设置!$B$24)) -> 0 | T18: =MAX(0,M18-N18-Q18-R18) -> 0 | U18: =P18-Q18 -> 17638.75 | V18: =MAX(0,H18+G18-S18) -> 326185.12 | W18: =SUM($C$7:C18)-SUM($K$7:K18) -> 280800 | X18: =W18/D18 -> 326511.63 | Y18: =V18+U18 -> 343823.87 | Z18: =Y18-X18 -> 17312.238 | AA18: =N18+Q18+R18+T18-M18 -> 0
... A54: =EDATE(DATE(YEAR(参数设置!$B$4),MONTH(参数设置!$B$4),1),ROW()-7) -> 47665 | B54: 期后：内部池优先+外部池 | C54: =IF(AND(ROW()-6<=参数设置!$B$6,OR(B54=策略字典!$A$1,B54=策略字典!$A$2)),参数设置!$B$5,0) -> 0 | D54: =参数设置!$B$7 -> 0.86 | E54: =IF(B54=策略字典!$A$1,C54/D54,0) -> 0 | F54: =E54*参数设置!$B$23 -> 0 | G54: =E54-F54 -> 0 | H54: =IF(ROW()=7,0,V53) -> 87713.493 | I54: =(H54+G54)*参数设置!$B$19/参数设置!$B$20 -> 1096.4187 | J54: =IF(ROW()=7,0,I53) -> 1096.4187 | K54: =SUMIFS(贷款明细!$I$4:$I$435,贷款明细!$G$4:$G$435,">="&A54,贷款明细!$G$4:$G$435,"<"&EDATE(A54,1)) -> 0 | L54: =SUMIFS(贷款明细!$J$4:$J$435,贷款明细!$G$4:$G$435,">="&A54,贷款明细!$G$4:$G$435,"<"&EDATE(A54,1)) -> 0 | M54: =(K54+L54)/D54 -> 0 | N54: =IF(B54=策略字典!$A$2,MIN(C54,K54)/D54,0) -> 0 | O54: =IF(ROW()=7,0,U53) -> 12380.468 | P54: =O54+J54 -> 13476.886 | Q54: =MIN(P54,MAX(0,M54-N54)) -> 0 | R54: =IF(B54=策略字典!$A$3,MIN(H54+G54,MAX(0,M54-N54-Q54)),0) -> 0 | S54: =IF(R54=0,0,R54/(1-参数设置!$B$24)) -> 0 | T54: =MAX(0,M54-N54-Q54-R54) -> 0 | U54: =P54-Q54 -> 13476.886 | V54: =MAX(0,H54+G54-S54) -> 87713.493 | W54: =SUM($C$7:C54)-SUM($K$7:K54) -> 0 | X54: =W54/D54 -> 0 | Y54: =V54+U54 -> 101190.38 | Z54: =Y54-X54 -> 101190.38 | AA54: =N54+Q54+R54+T54-M54 -> 0
A55: 累计/期末 | C55: =SUM(C7:C54) -> 561600 | E55: =SUM(E7:E54) -> 326511.63 | F55: =SUM(F7:F54) -> 326.51163 | G55: =SUM(G7:G54) -> 326185.12 | H55: =H54 -> 87713.493 | I55: =SUM(I7:I54) -> 124731.83 | J55: =SUM(J7:J54) -> 123635.41 | K55: =SUM(K7:K54) -> 561600 | L55: =SUM(L7:L54) -> 18816.84 | M55: =SUM(M7:M54) -> 674903.3 | N55: =SUM(N7:N54) -> 326511.63 | O55: =O54 -> 12380.468 | P55: =P54 -> 13476.886 | Q55: =SUM(Q7:Q54) -> 110158.52 | R55: =SUM(R7:R54) -> 238233.15 | S55: =SUM(S7:S54) -> 238471.62 | T55: =SUM(T7:T54) -> 0 | U55: =U54 -> 13476.886 | V55: =V54 -> 87713.493 | W55: =W54 -> 0 | X55: =X54 -> 0 | Y55: =Y54 -> 101190.38 | Z55: =Z54 -> 101190.38

Sheet 贷款明细
A1: 贷款明细（逐笔Actual/360计息）
A3: 贷款批次 | B3: 策略月份 | C3: 放款日 | D3: 贷款本金（人民币） | E3: 期数 | F3: 本期起始日 | G3: 本期还款日 | H3: 计息天数 | I3: 当期本金（人民币） | J3: 当期利息（人民币） | K3: 当期还款（人民币） | L3: 本金到期日 | M3: 是否启用
A4: 1 | B4: 1 | C4: =EDATE(参数设置!$B$4,A4-1) -> 46244 | D4: =IF(AND(A4<=参数设置!$B$6,OR(INDEX(月度资金流!$B$7:$B$42,A4)="策略一：消费贷款+买基金",INDEX(月度资金流!$B$7:$B$42,A4)="策略二：新贷偿还旧贷")),参数设置!$B$5,0) -> 23400 | E4: 1 | F4: =IF(E4=1,C4,G3) -> 46244 | G4: =IF(E4<参数设置!$B$14,DATE(YEAR(EDATE(C4,E4+1)),MONTH(EDATE(C4,E4+1)),参数设置!$B$15),EDATE(C4,参数设置!$B$14)) -> 46300 | H4: =G4-F4 -> 56 | I4: =IF(E4=参数设置!$B$14,D4,0) -> 0 | J4: =IF(M4=1,ROUND(D4*参数设置!$B$12*H4/参数设置!$B$13,参数设置!$B$16),0) -> 120.12 | K4: =I4+J4 -> 120.12 | L4: =EDATE(C4,参数设置!$B$14) -> 46609 | M4: =--(D4>0) -> 1
A5: 1 | B5: 1 | C5: =EDATE(参数设置!$B$4,A5-1) -> 46244 | D5: =IF(AND(A5<=参数设置!$B$6,OR(INDEX(月度资金流!$B$7:$B$42,A5)="策略一：消费贷款+买基金",INDEX(月度资金流!$B$7:$B$42,A5)="策略二：新贷偿还旧贷")),参数设置!$B$5,0) -> 23400 | E5: 2 | F5: =IF(E5=1,C5,G4) -> 46300 | G5: =IF(E5<参数设置!$B$14,DATE(YEAR(EDATE(C5,E5+1)),MONTH(EDATE(C5,E5+1)),参数设置!$B$15),EDATE(C5,参数设置!$B$14)) -> 46331 | H5: =G5-F5 -> 31 | I5: =IF(E5=参数设置!$B$14,D5,0) -> 0 | J5: =IF(M5=1,ROUND(D5*参数设置!$B$12*H5/参数设置!$B$13,参数设置!$B$16),0) -> 66.5 | K5: =I5+J5 -> 66.5 | L5: =EDATE(C5,参数设置!$B$14) -> 46609 | M5: =--(D5>0) -> 1
A6: 1 | B6: 1 | C6: =EDATE(参数设置!$B$4,A6-1) -> 46244 | D6: =IF(AND(A6<=参数设置!$B$6,OR(INDEX(月度资金流!$B$7:$B$42,A6)="策略一：消费贷款+买基金",INDEX(月度资金流!$B$7:$B$42,A6)="策略二：新贷偿还旧贷")),参数设置!$B$5,0) -> 23400 | E6: 3 | F6: =IF(E6=1,C6,G5) -> 46331 | G6: =IF(E6<参数设置!$B$14,DATE(YEAR(EDATE(C6,E6+1)),MONTH(EDATE(C6,E6+1)),参数设置!$B$15),EDATE(C6,参数设置!$B$14)) -> 46361 | H6: =G6-F6 -> 30 | I6: =IF(E6=参数设置!$B$14,D6,0) -> 0 | J6: =IF(M6=1,ROUND(D6*参数设置!$B$12*H6/参数设置!$B$13,参数设置!$B$16),0) -> 64.35 | K6: =I6+J6 -> 64.35 | L6: =EDATE(C6,参数设置!$B$14) -> 46609 | M6: =--(D6>0) -> 1
A7: 1 | B7: 1 | C7: =EDATE(参数设置!$B$4,A7-1) -> 46244 | D7: =IF(AND(A7<=参数设置!$B$6,OR(INDEX(月度资金流!$B$7:$B$42,A7)="策略一：消费贷款+买基金",INDEX(月度资金流!$B$7:$B$42,A7)="策略二：新贷偿还旧贷")),参数设置!$B$5,0) -> 23400 | E7: 4 | F7: =IF(E7=1,C7,G6) -> 46361 | G7: =IF(E7<参数设置!$B$14,DATE(YEAR(EDATE(C7,E7+1)),MONTH(EDATE(C7,E7+1)),参数设置!$B$15),EDATE(C7,参数设置!$B$14)) -> 46392 | H7: =G7-F7 -> 31 | I7: =IF(E7=参数设置!$B$14,D7,0) -> 0 | J7: =IF(M7=1,ROUND(D7*参数设置!$B$12*H7/参数设置!$B$13,参数设置!$B$16),0) -> 66.5 | K7: =I7+J7 -> 66.5 | L7: =EDATE(C7,参数设置!$B$14) -> 46609 | M7: =--(D7>0) -> 1
A8: 1 | B8: 1 | C8: =EDATE(参数设置!$B$4,A8-1) -> 46244 | D8: =IF(AND(A8<=参数设置!$B$6,OR(INDEX(月度资金流!$B$7:$B$42,A8)="策略一：消费贷款+买基金",INDEX(月度资金流!$B$7:$B$42,A8)="策略二：新贷偿还旧贷")),参数设置!$B$5,0) -> 23400 | E8: 5 | F8: =IF(E8=1,C8,G7) -> 46392 | G8: =IF(E8<参数设置!$B$14,DATE(YEAR(EDATE(C8,E8+1)),MONTH(EDATE(C8,E8+1)),参数设置!$B$15),EDATE(C8,参数设置!$B$14)) -> 46423 | H8: =G8-F8 -> 31 | I8: =IF(E8=参数设置!$B$14,D8,0) -> 0 | J8: =IF(M8=1,ROUND(D8*参数设置!$B$12*H8/参数设置!$B$13,参数设置!$B$16),0) -> 66.5 | K8: =I8+J8 -> 66.5 | L8: =EDATE(C8,参数设置!$B$14) -> 46609 | M8: =--(D8>0) -> 1
A9: 1 | B9: 1 | C9: =EDATE(参数设置!$B$4,A9-1) -> 46244 | D9: =IF(AND(A9<=参数设置!$B$6,OR(INDEX(月度资金流!$B$7:$B$42,A9)="策略一：消费贷款+买基金",INDEX(月度资金流!$B$7:$B$42,A9)="策略二：新贷偿还旧贷")),参数设置!$B$5,0) -> 23400 | E9: 6 | F9: =IF(E9=1,C9,G8) -> 46423 | G9: =IF(E9<参数设置!$B$14,DATE(YEAR(EDATE(C9,E9+1)),MONTH(EDATE(C9,E9+1)),参数设置!$B$15),EDATE(C9,参数设置!$B$14)) -> 46451 | H9: =G9-F9 -> 28 | I9: =IF(E9=参数设置!$B$14,D9,0) -> 0 | J9: =IF(M9=1,ROUND(D9*参数设置!$B$12*H9/参数设置!$B$13,参数设置!$B$16),0) -> 60.06 | K9: =I9+J9 -> 60.06 | L9: =EDATE(C9,参数设置!$B$14) -> 46609 | M9: =--(D9>0) -> 1
A10: 1 | B10: 1 | C10: =EDATE(参数设置!$B$4,A10-1) -> 46244 | D10: =IF(AND(A10<=参数设置!$B$6,OR(INDEX(月度资金流!$B$7:$B$42,A10)="策略一：消费贷款+买基金",INDEX(月度资金流!$B$7:$B$42,A10)="策略二：新贷偿还旧贷")),参数设置!$B$5,0) -> 23400 | E10: 7 | F10: =IF(E10=1,C10,G9) -> 46451 | G10: =IF(E10<参数设置!$B$14,DATE(YEAR(EDATE(C10,E10+1)),MONTH(EDATE(C10,E10+1)),参数设置!$B$15),EDATE(C10,参数设置!$B$14)) -> 46482 | H10: =G10-F10 -> 31 | I10: =IF(E10=参数设置!$B$14,D10,0) -> 0 | J10: =IF(M10=1,ROUND(D10*参数设置!$B$12*H10/参数设置!$B$13,参数设置!$B$16),0) -> 66.5 | K10: =I10+J10 -> 66.5 | L10: =EDATE(C10,参数设置!$B$14) -> 46609 | M10: =--(D10>0) -> 1
A11: 1 | B11: 1 | C11: =EDATE(参数设置!$B$4,A11-1) -> 46244 | D11: =IF(AND(A11<=参数设置!$B$6,OR(INDEX(月度资金流!$B$7:$B$42,A11)="策略一：消费贷款+买基金",INDEX(月度资金流!$B$7:$B$42,A11)="策略二：新贷偿还旧贷")),参数设置!$B$5,0) -> 23400 | E11: 8 | F11: =IF(E11=1,C11,G10) -> 46482 | G11: =IF(E11<参数设置!$B$14,DATE(YEAR(EDATE(C11,E11+1)),MONTH(EDATE(C11,E11+1)),参数设置!$B$15),EDATE(C11,参数设置!$B$14)) -> 46512 | H11: =G11-F11 -> 30 | I11: =IF(E11=参数设置!$B$14,D11,0) -> 0 | J11: =IF(M11=1,ROUND(D11*参数设置!$B$12*H11/参数设置!$B$13,参数设置!$B$16),0) -> 64.35 | K11: =I11+J11 -> 64.35 | L11: =EDATE(C11,参数设置!$B$14) -> 46609 | M11: =--(D11>0) -> 1
A12: 1 | B12: 1 | C12: =EDATE(参数设置!$B$4,A12-1) -> 46244 | D12: =IF(AND(A12<=参数设置!$B$6,OR(INDEX(月度资金流!$B$7:$B$42,A12)="策略一：消费贷款+买基金",INDEX(月度资金流!$B$7:$B$42,A12)="策略二：新贷偿还旧贷")),参数设置!$B$5,0) -> 23400 | E12: 9 | F12: =IF(E12=1,C12,G11) -> 46512 | G12: =IF(E12<参数设置!$B$14,DATE(YEAR(EDATE(C12,E12+1)),MONTH(EDATE(C12,E12+1)),参数设置!$B$15),EDATE(C12,参数设置!$B$14)) -> 46543 | H12: =G12-F12 -> 31 | I12: =IF(E12=参数设置!$B$14,D12,0) -> 0 | J12: =IF(M12=1,ROUND(D12*参数设置!$B$12*H12/参数设置!$B$13,参数设置!$B$16),0) -> 66.5 | K12: =I12+J12 -> 66.5 | L12: =EDATE(C12,参数设置!$B$14) -> 46609 | M12: =--(D12>0) -> 1
A13: 1 | B13: 1 | C13: =EDATE(参数设置!$B$4,A13-1) -> 46244 | D13: =IF(AND(A13<=参数设置!$B$6,OR(INDEX(月度资金流!$B$7:$B$42,A13)="策略一：消费贷款+买基金",INDEX(月度资金流!$B$7:$B$42,A13)="策略二：新贷偿还旧贷")),参数设置!$B$5,0) -> 23400 | E13: 10 | F13: =IF(E13=1,C13,G12) -> 46543 | G13: =IF(E13<参数设置!$B$14,DATE(YEAR(EDATE(C13,E13+1)),MONTH(EDATE(C13,E13+1)),参数设置!$B$15),EDATE(C13,参数设置!$B$14)) -> 46573 | H13: =G13-F13 -> 30 | I13: =IF(E13=参数设置!$B$14,D13,0) -> 0 | J13: =IF(M13=1,ROUND(D13*参数设置!$B$12*H13/参数设置!$B$13,参数设置!$B$16),0) -> 64.35 | K13: =I13+J13 -> 64.35 | L13: =EDATE(C13,参数设置!$B$14) -> 46609 | M13: =--(D13>0) -> 1
A14: 1 | B14: 1 | C14: =EDATE(参数设置!$B$4,A14-1) -> 46244 | D14: =IF(AND(A14<=参数设置!$B$6,OR(INDEX(月度资金流!$B$7:$B$42,A14)="策略一：消费贷款+买基金",INDEX(月度资金流!$B$7:$B$42,A14)="策略二：新贷偿还旧贷")),参数设置!$B$5,0) -> 23400 | E14: 11 | F14: =IF(E14=1,C14,G13) -> 46573 | G14: =IF(E14<参数设置!$B$14,DATE(YEAR(EDATE(C14,E14+1)),MONTH(EDATE(C14,E14+1)),参数设置!$B$15),EDATE(C14,参数设置!$B$14)) -> 46604 | H14: =G14-F14 -> 31 | I14: =IF(E14=参数设置!$B$14,D14,0) -> 0 | J14: =IF(M14=1,ROUND(D14*参数设置!$B$12*H14/参数设置!$B$13,参数设置!$B$16),0) -> 66.5 | K14: =I14+J14 -> 66.5 | L14: =EDATE(C14,参数设置!$B$14) -> 46609 | M14: =--(D14>0) -> 1
A15: 1 | B15: 1 | C15: =EDATE(参数设置!$B$4,A15-1) -> 46244 | D15: =IF(AND(A15<=参数设置!$B$6,OR(INDEX(月度资金流!$B$7:$B$42,A15)="策略一：消费贷款+买基金",INDEX(月度资金流!$B$7:$B$42,A15)="策略二：新贷偿还旧贷")),参数设置!$B$5,0) -> 23400 | E15: 12 | F15: =IF(E15=1,C15,G14) -> 46604 | G15: =IF(E15<参数设置!$B$14,DATE(YEAR(EDATE(C15,E15+1)),MONTH(EDATE(C15,E15+1)),参数设置!$B$15),EDATE(C15,参数设置!$B$14)) -> 46609 | H15: =G15-F15 -> 5 | I15: =IF(E15=参数设置!$B$14,D15,0) -> 23400 | J15: =IF(M15=1,ROUND(D15*参数设置!$B$12*H15/参数设置!$B$13,参数设置!$B$16),0) -> 10.73 | K15: =I15+J15 -> 23410.73 | L15: =EDATE(C15,参数设置!$B$14) -> 46609 | M15: =--(D15>0) -> 1
... A435: 36 | B435: 36 | C435: =EDATE(参数设置!$B$4,A435-1) -> 47309 | D435: =IF(AND(A435<=参数设置!$B$6,OR(INDEX(月度资金流!$B$7:$B$42,A435)="策略一：消费贷款+买基金",INDEX(月度资金流!$B$7:$B$42,A435)="策略二：新贷偿还旧贷")),参数设置!$B$5,0) -> 0 | E435: 12 | F435: =IF(E435=1,C435,G434) -> 47669 | G435: =IF(E435<参数设置!$B$14,DATE(YEAR(EDATE(C435,E435+1)),MONTH(EDATE(C435,E435+1)),参数设置!$B$15),EDATE(C435,参数设置!$B$14)) -> 47674 | H435: =G435-F435 -> 5 | I435: =IF(E435=参数设置!$B$14,D435,0) -> 0 | J435: =IF(M435=1,ROUND(D435*参数设置!$B$12*H435/参数设置!$B$13,参数设置!$B$16),0) -> 0 | K435: =I435+J435 -> 0 | L435: =EDATE(C435,参数设置!$B$14) -> 47674 | M435: =--(D435>0) -> 0

Sheet 策略字典
A1: 策略一：消费贷款+买基金
A2: 策略二：新贷偿还旧贷
A3: 策略三：卖基金偿还
A4: 期后：内部池优先+外部池
