Workbook

Sheet 模型说明
A1: 中银E贷 + 香港港币基金滚动策略模型
A3: 用途 | B3: 比较“每月直接换汇消费”与“每月人民币贷款消费，同时将等值港币投入按月分红基金”的现金流、收益、利息、到期本金及净资产。
A5: 核心口径 | B5: 贷款利息按 Actual/360：剩余本金 × 年利率 × 实际计息天数 ÷ 360；按期付息，到期还本。
A6: 投资口径 | B6: 5%默认解释为年化现金分红率，按月计提，除息日28日，次月8日发放；默认不考虑基金净值涨跌、税费及手续费。
A7: 汇率口径 | B7: “人民币/港币”表示1港币可兑换多少人民币。月度汇率可逐月改动，贷款还款也按对应月份的汇率折算为港币。
A9: 使用方法 | B9: 1）在“参数设置”修改蓝色字体；2）在“月度汇总”E列逐月输入实际/假设汇率；3）查看顶部KPI及图表；4）在“贷款明细”核对每笔贷款到期日和逐期利息。
A11: 重要提示 | B11: 本模型用于情景分析，不构成投资或借贷建议。滚动借款会形成集中到期本金，基金收益并非保证；若人民币升值、基金净值下跌或贷款利率上升，策略可能亏损。
A13: 颜色说明 | B13: 蓝色字体＝可修改输入；黑色＝公式；绿色＝跨工作表链接；灰色＝静态说明；黄色底纹＝关键假设。

Sheet 参数设置
A1: 参数设置
A3: 时间及消费假设
A4: 模型开始日 | B4: 46244 | C4: 每月贷款及基金申购日以该日的“日”为准
A5: 每月人民币消费/贷款金额 | B5: 23400 | C5: 每月在中国大陆消费，由当月新贷款覆盖
A6: 新增贷款月数 | B6: 24 | C6: 预先支持1至36个月
A7: 汇率基准（人民币/港币） | B7: 0.92 | C7: 1港币可兑换的人民币；月度表可逐月覆盖
A9: 中银E贷假设
A10: 年利率 | B10: 0.033 | C10: 根据截图试算
A11: 计息年基数 | B11: 360 | C11: Actual/360
A12: 贷款期限（月） | B12: 12 | C12: 每笔贷款期限
A13: 每月结息日 | B13: 5 | C13: 首个结息日设为放款后第二个月的该日
A14: 每期金额取整位数 | B14: 2 | C14: 人民币“分”
A16: 港币基金假设
A17: 预计年化分红率 | B17: 0.05 | C17: 按月分红，非保证收益
A18: 每年分红次数 | B18: 12 | C18: 默认每月一次
A19: 每月除息日 | B19: 28 | C19: 当月10日申购假设可参与当月除息
A20: 分红发放日 | B20: 8 | C20: 当月计提、次月8日发放
A21: 申购/赎回费用率 | B21: 0 | C21: 如有收费可填写

Sheet 月度汇总
A1: 月度汇总与策略对比
A3: 累计基金投入（港币） | E3: 累计已收分红（港币） | I3: 累计贷款利息（人民币） | M3: 期末未偿本金（人民币） | Q3: 策略期末净资产（港币）
A4: =SUM(H7:H54) -> 610434.78 | E4: =SUM(K7:K54) -> 90293.478 | I4: =SUM(N7:N54) -> 18816.84 | M4: =INDEX(S7:S54,参数设置!B6+参数设置!B12) -> 0 | Q4: =INDEX(V7:V54,参数设置!B6+参数设置!B12) -> 649753.43
A6: 月份 | B6: 贷款批次 | C6: 贷款日 | D6: 当月消费/新贷款（人民币） | E6: 汇率（人民币/港币） | F6: 直接换汇所需港币 | G6: 基金申购费用（港币） | H6: 基金净投入（港币） | I6: 期末基金本金（港币） | J6: 当月应计分红（港币） | K6: 当月收到分红（港币） | L6: 累计分红（港币） | M6: 偿还本金（人民币） | N6: 支付利息（人民币） | O6: 还款总额（人民币） | P6: 还款折港币 | Q6: 净现金流（港币） | R6: 到期本金提示（人民币） | S6: 期末未偿本金（人民币） | T6: 负债折港币 | U6: 基金资产+分红（港币） | V6: 策略净资产（港币）
A7: =EDATE(DATE(YEAR(参数设置!$B$4),MONTH(参数设置!$B$4),1),ROW()-7) -> 46235 | B7: =IF(ROW()-6<=参数设置!$B$6,ROW()-6,"") -> 1 | C7: =IF(B7="","",EDATE(参数设置!$B$4,B7-1)) -> 46244 | D7: =IF(B7="",0,参数设置!$B$5) -> 23400 | E7: =参数设置!$B$7 -> 0.92 | F7: =IF(D7=0,0,D7/E7) -> 25434.783 | G7: =F7*参数设置!$B$21 -> 0 | H7: =F7-G7 -> 25434.783 | I7: =IF(ROW()=7,H7,I6+H7) -> 25434.783 | J7: =I7*参数设置!$B$17/参数设置!$B$18 -> 105.97826 | K7: =IF(ROW()=7,0,J6) -> 0 | L7: =IF(ROW()=7,K7,L6+K7) -> 0 | M7: =SUMIFS(贷款明细!$H$4:$H$435,贷款明细!$F$4:$F$435,">="&A7,贷款明细!$F$4:$F$435,"<"&EDATE(A7,1)) -> 0 | N7: =SUMIFS(贷款明细!$I$4:$I$435,贷款明细!$F$4:$F$435,">="&A7,贷款明细!$F$4:$F$435,"<"&EDATE(A7,1)) -> 0 | O7: =M7+N7 -> 0 | P7: =O7/E7 -> 0 | Q7: =-H7+K7-P7 -> -25434.783 | R7: =M7 -> 0 | S7: =SUM($D$7:D7)-SUM($M$7:M7) -> 23400 | T7: =S7/E7 -> 25434.783 | U7: =I7+L7 -> 25434.783 | V7: =U7-T7-SUM($N$7:N7)/E7 -> 0
A8: =EDATE(DATE(YEAR(参数设置!$B$4),MONTH(参数设置!$B$4),1),ROW()-7) -> 46266 | B8: =IF(ROW()-6<=参数设置!$B$6,ROW()-6,"") -> 2 | C8: =IF(B8="","",EDATE(参数设置!$B$4,B8-1)) -> 46275 | D8: =IF(B8="",0,参数设置!$B$5) -> 23400 | E8: =参数设置!$B$7 -> 0.92 | F8: =IF(D8=0,0,D8/E8) -> 25434.783 | G8: =F8*参数设置!$B$21 -> 0 | H8: =F8-G8 -> 25434.783 | I8: =IF(ROW()=7,H8,I7+H8) -> 50869.565 | J8: =I8*参数设置!$B$17/参数设置!$B$18 -> 211.95652 | K8: =IF(ROW()=7,0,J7) -> 105.97826 | L8: =IF(ROW()=7,K8,L7+K8) -> 105.97826 | M8: =SUMIFS(贷款明细!$H$4:$H$435,贷款明细!$F$4:$F$435,">="&A8,贷款明细!$F$4:$F$435,"<"&EDATE(A8,1)) -> 0 | N8: =SUMIFS(贷款明细!$I$4:$I$435,贷款明细!$F$4:$F$435,">="&A8,贷款明细!$F$4:$F$435,"<"&EDATE(A8,1)) -> 0 | O8: =M8+N8 -> 0 | P8: =O8/E8 -> 0 | Q8: =-H8+K8-P8 -> -25328.804 | R8: =M8 -> 0 | S8: =SUM($D$7:D8)-SUM($M$7:M8) -> 46800 | T8: =S8/E8 -> 50869.565 | U8: =I8+L8 -> 50975.543 | V8: =U8-T8-SUM($N$7:N8)/E8 -> 105.97826
A9: =EDATE(DATE(YEAR(参数设置!$B$4),MONTH(参数设置!$B$4),1),ROW()-7) -> 46296 | B9: =IF(ROW()-6<=参数设置!$B$6,ROW()-6,"") -> 3 | C9: =IF(B9="","",EDATE(参数设置!$B$4,B9-1)) -> 46305 | D9: =IF(B9="",0,参数设置!$B$5) -> 23400 | E9: =参数设置!$B$7 -> 0.92 | F9: =IF(D9=0,0,D9/E9) -> 25434.783 | G9: =F9*参数设置!$B$21 -> 0 | H9: =F9-G9 -> 25434.783 | I9: =IF(ROW()=7,H9,I8+H9) -> 76304.348 | J9: =I9*参数设置!$B$17/参数设置!$B$18 -> 317.93478 | K9: =IF(ROW()=7,0,J8) -> 211.95652 | L9: =IF(ROW()=7,K9,L8+K9) -> 317.93478 | M9: =SUMIFS(贷款明细!$H$4:$H$435,贷款明细!$F$4:$F$435,">="&A9,贷款明细!$F$4:$F$435,"<"&EDATE(A9,1)) -> 0 | N9: =SUMIFS(贷款明细!$I$4:$I$435,贷款明细!$F$4:$F$435,">="&A9,贷款明细!$F$4:$F$435,"<"&EDATE(A9,1)) -> 120.12 | O9: =M9+N9 -> 120.12 | P9: =O9/E9 -> 130.56522 | Q9: =-H9+K9-P9 -> -25353.391 | R9: =M9 -> 0 | S9: =SUM($D$7:D9)-SUM($M$7:M9) -> 70200 | T9: =S9/E9 -> 76304.348 | U9: =I9+L9 -> 76622.283 | V9: =U9-T9-SUM($N$7:N9)/E9 -> 187.36957
A10: =EDATE(DATE(YEAR(参数设置!$B$4),MONTH(参数设置!$B$4),1),ROW()-7) -> 46327 | B10: =IF(ROW()-6<=参数设置!$B$6,ROW()-6,"") -> 4 | C10: =IF(B10="","",EDATE(参数设置!$B$4,B10-1)) -> 46336 | D10: =IF(B10="",0,参数设置!$B$5) -> 23400 | E10: =参数设置!$B$7 -> 0.92 | F10: =IF(D10=0,0,D10/E10) -> 25434.783 | G10: =F10*参数设置!$B$21 -> 0 | H10: =F10-G10 -> 25434.783 | I10: =IF(ROW()=7,H10,I9+H10) -> 101739.13 | J10: =I10*参数设置!$B$17/参数设置!$B$18 -> 423.91304 | K10: =IF(ROW()=7,0,J9) -> 317.93478 | L10: =IF(ROW()=7,K10,L9+K10) -> 635.86957 | M10: =SUMIFS(贷款明细!$H$4:$H$435,贷款明细!$F$4:$F$435,">="&A10,贷款明细!$F$4:$F$435,"<"&EDATE(A10,1)) -> 0 | N10: =SUMIFS(贷款明细!$I$4:$I$435,贷款明细!$F$4:$F$435,">="&A10,贷款明细!$F$4:$F$435,"<"&EDATE(A10,1)) -> 186.62 | O10: =M10+N10 -> 186.62 | P10: =O10/E10 -> 202.84783 | Q10: =-H10+K10-P10 -> -25319.696 | R10: =M10 -> 0 | S10: =SUM($D$7:D10)-SUM($M$7:M10) -> 93600 | T10: =S10/E10 -> 101739.13 | U10: =I10+L10 -> 102375 | V10: =U10-T10-SUM($N$7:N10)/E10 -> 302.45652
A11: =EDATE(DATE(YEAR(参数设置!$B$4),MONTH(参数设置!$B$4),1),ROW()-7) -> 46357 | B11: =IF(ROW()-6<=参数设置!$B$6,ROW()-6,"") -> 5 | C11: =IF(B11="","",EDATE(参数设置!$B$4,B11-1)) -> 46366 | D11: =IF(B11="",0,参数设置!$B$5) -> 23400 | E11: =参数设置!$B$7 -> 0.92 | F11: =IF(D11=0,0,D11/E11) -> 25434.783 | G11: =F11*参数设置!$B$21 -> 0 | H11: =F11-G11 -> 25434.783 | I11: =IF(ROW()=7,H11,I10+H11) -> 127173.91 | J11: =I11*参数设置!$B$17/参数设置!$B$18 -> 529.8913 | K11: =IF(ROW()=7,0,J10) -> 423.91304 | L11: =IF(ROW()=7,K11,L10+K11) -> 1059.7826 | M11: =SUMIFS(贷款明细!$H$4:$H$435,贷款明细!$F$4:$F$435,">="&A11,贷款明细!$F$4:$F$435,"<"&EDATE(A11,1)) -> 0 | N11: =SUMIFS(贷款明细!$I$4:$I$435,贷款明细!$F$4:$F$435,">="&A11,贷款明细!$F$4:$F$435,"<"&EDATE(A11,1)) -> 248.82 | O11: =M11+N11 -> 248.82 | P11: =O11/E11 -> 270.45652 | Q11: =-H11+K11-P11 -> -25281.326 | R11: =M11 -> 0 | S11: =SUM($D$7:D11)-SUM($M$7:M11) -> 117000 | T11: =S11/E11 -> 127173.91 | U11: =I11+L11 -> 128233.7 | V11: =U11-T11-SUM($N$7:N11)/E11 -> 455.91304
A12: =EDATE(DATE(YEAR(参数设置!$B$4),MONTH(参数设置!$B$4),1),ROW()-7) -> 46388 | B12: =IF(ROW()-6<=参数设置!$B$6,ROW()-6,"") -> 6 | C12: =IF(B12="","",EDATE(参数设置!$B$4,B12-1)) -> 46397 | D12: =IF(B12="",0,参数设置!$B$5) -> 23400 | E12: =参数设置!$B$7 -> 0.92 | F12: =IF(D12=0,0,D12/E12) -> 25434.783 | G12: =F12*参数设置!$B$21 -> 0 | H12: =F12-G12 -> 25434.783 | I12: =IF(ROW()=7,H12,I11+H12) -> 152608.7 | J12: =I12*参数设置!$B$17/参数设置!$B$18 -> 635.86957 | K12: =IF(ROW()=7,0,J11) -> 529.8913 | L12: =IF(ROW()=7,K12,L11+K12) -> 1589.6739 | M12: =SUMIFS(贷款明细!$H$4:$H$435,贷款明细!$F$4:$F$435,">="&A12,贷款明细!$F$4:$F$435,"<"&EDATE(A12,1)) -> 0 | N12: =SUMIFS(贷款明细!$I$4:$I$435,贷款明细!$F$4:$F$435,">="&A12,贷款明细!$F$4:$F$435,"<"&EDATE(A12,1)) -> 319.62 | O12: =M12+N12 -> 319.62 | P12: =O12/E12 -> 347.41304 | Q12: =-H12+K12-P12 -> -25252.304 | R12: =M12 -> 0 | S12: =SUM($D$7:D12)-SUM($M$7:M12) -> 140400 | T12: =S12/E12 -> 152608.7 | U12: =I12+L12 -> 154198.37 | V12: =U12-T12-SUM($N$7:N12)/E12 -> 638.3913
A13: =EDATE(DATE(YEAR(参数设置!$B$4),MONTH(参数设置!$B$4),1),ROW()-7) -> 46419 | B13: =IF(ROW()-6<=参数设置!$B$6,ROW()-6,"") -> 7 | C13: =IF(B13="","",EDATE(参数设置!$B$4,B13-1)) -> 46428 | D13: =IF(B13="",0,参数设置!$B$5) -> 23400 | E13: =参数设置!$B$7 -> 0.92 | F13: =IF(D13=0,0,D13/E13) -> 25434.783 | G13: =F13*参数设置!$B$21 -> 0 | H13: =F13-G13 -> 25434.783 | I13: =IF(ROW()=7,H13,I12+H13) -> 178043.48 | J13: =I13*参数设置!$B$17/参数设置!$B$18 -> 741.84783 | K13: =IF(ROW()=7,0,J12) -> 635.86957 | L13: =IF(ROW()=7,K13,L12+K13) -> 2225.5435 | M13: =SUMIFS(贷款明细!$H$4:$H$435,贷款明细!$F$4:$F$435,">="&A13,贷款明细!$F$4:$F$435,"<"&EDATE(A13,1)) -> 0 | N13: =SUMIFS(贷款明细!$I$4:$I$435,贷款明细!$F$4:$F$435,">="&A13,贷款明细!$F$4:$F$435,"<"&EDATE(A13,1)) -> 388.27 | O13: =M13+N13 -> 388.27 | P13: =O13/E13 -> 422.03261 | Q13: =-H13+K13-P13 -> -25220.946 | R13: =M13 -> 0 | S13: =SUM($D$7:D13)-SUM($M$7:M13) -> 163800 | T13: =S13/E13 -> 178043.48 | U13: =I13+L13 -> 180269.02 | V13: =U13-T13-SUM($N$7:N13)/E13 -> 852.22826
A14: =EDATE(DATE(YEAR(参数设置!$B$4),MONTH(参数设置!$B$4),1),ROW()-7) -> 46447 | B14: =IF(ROW()-6<=参数设置!$B$6,ROW()-6,"") -> 8 | C14: =IF(B14="","",EDATE(参数设置!$B$4,B14-1)) -> 46456 | D14: =IF(B14="",0,参数设置!$B$5) -> 23400 | E14: =参数设置!$B$7 -> 0.92 | F14: =IF(D14=0,0,D14/E14) -> 25434.783 | G14: =F14*参数设置!$B$21 -> 0 | H14: =F14-G14 -> 25434.783 | I14: =IF(ROW()=7,H14,I13+H14) -> 203478.26 | J14: =I14*参数设置!$B$17/参数设置!$B$18 -> 847.82609 | K14: =IF(ROW()=7,0,J13) -> 741.84783 | L14: =IF(ROW()=7,K14,L13+K14) -> 2967.3913 | M14: =SUMIFS(贷款明细!$H$4:$H$435,贷款明细!$F$4:$F$435,">="&A14,贷款明细!$F$4:$F$435,"<"&EDATE(A14,1)) -> 0 | N14: =SUMIFS(贷款明细!$I$4:$I$435,贷款明细!$F$4:$F$435,">="&A14,贷款明细!$F$4:$F$435,"<"&EDATE(A14,1)) -> 416.13 | O14: =M14+N14 -> 416.13 | P14: =O14/E14 -> 452.31522 | Q14: =-H14+K14-P14 -> -25145.25 | R14: =M14 -> 0 | S14: =SUM($D$7:D14)-SUM($M$7:M14) -> 187200 | T14: =S14/E14 -> 203478.26 | U14: =I14+L14 -> 206445.65 | V14: =U14-T14-SUM($N$7:N14)/E14 -> 1141.7609
A15: =EDATE(DATE(YEAR(参数设置!$B$4),MONTH(参数设置!$B$4),1),ROW()-7) -> 46478 | B15: =IF(ROW()-6<=参数设置!$B$6,ROW()-6,"") -> 9 | C15: =IF(B15="","",EDATE(参数设置!$B$4,B15-1)) -> 46487 | D15: =IF(B15="",0,参数设置!$B$5) -> 23400 | E15: =参数设置!$B$7 -> 0.92 | F15: =IF(D15=0,0,D15/E15) -> 25434.783 | G15: =F15*参数设置!$B$21 -> 0 | H15: =F15-G15 -> 25434.783 | I15: =IF(ROW()=7,H15,I14+H15) -> 228913.04 | J15: =I15*参数设置!$B$17/参数设置!$B$18 -> 953.80435 | K15: =IF(ROW()=7,0,J14) -> 847.82609 | L15: =IF(ROW()=7,K15,L14+K15) -> 3815.2174 | M15: =SUMIFS(贷款明细!$H$4:$H$435,贷款明细!$F$4:$F$435,">="&A15,贷款明细!$F$4:$F$435,"<"&EDATE(A15,1)) -> 0 | N15: =SUMIFS(贷款明细!$I$4:$I$435,贷款明细!$F$4:$F$435,">="&A15,贷款明细!$F$4:$F$435,"<"&EDATE(A15,1)) -> 514.83 | O15: =M15+N15 -> 514.83 | P15: =O15/E15 -> 559.59783 | Q15: =-H15+K15-P15 -> -25146.554 | R15: =M15 -> 0 | S15: =SUM($D$7:D15)-SUM($M$7:M15) -> 210600 | T15: =S15/E15 -> 228913.04 | U15: =I15+L15 -> 232728.26 | V15: =U15-T15-SUM($N$7:N15)/E15 -> 1429.9891
A16: =EDATE(DATE(YEAR(参数设置!$B$4),MONTH(参数设置!$B$4),1),ROW()-7) -> 46508 | B16: =IF(ROW()-6<=参数设置!$B$6,ROW()-6,"") -> 10 | C16: =IF(B16="","",EDATE(参数设置!$B$4,B16-1)) -> 46517 | D16: =IF(B16="",0,参数设置!$B$5) -> 23400 | E16: =参数设置!$B$7 -> 0.92 | F16: =IF(D16=0,0,D16/E16) -> 25434.783 | G16: =F16*参数设置!$B$21 -> 0 | H16: =F16-G16 -> 25434.783 | I16: =IF(ROW()=7,H16,I15+H16) -> 254347.83 | J16: =I16*参数设置!$B$17/参数设置!$B$18 -> 1059.7826 | K16: =IF(ROW()=7,0,J15) -> 953.80435 | L16: =IF(ROW()=7,K16,L15+K16) -> 4769.0217 | M16: =SUMIFS(贷款明细!$H$4:$H$435,贷款明细!$F$4:$F$435,">="&A16,贷款明细!$F$4:$F$435,"<"&EDATE(A16,1)) -> 0 | N16: =SUMIFS(贷款明细!$I$4:$I$435,贷款明细!$F$4:$F$435,">="&A16,贷款明细!$F$4:$F$435,"<"&EDATE(A16,1)) -> 570.57 | O16: =M16+N16 -> 570.57 | P16: =O16/E16 -> 620.18478 | Q16: =-H16+K16-P16 -> -25101.163 | R16: =M16 -> 0 | S16: =SUM($D$7:D16)-SUM($M$7:M16) -> 234000 | T16: =S16/E16 -> 254347.83 | U16: =I16+L16 -> 259116.85 | V16: =U16-T16-SUM($N$7:N16)/E16 -> 1763.6087
A17: =EDATE(DATE(YEAR(参数设置!$B$4),MONTH(参数设置!$B$4),1),ROW()-7) -> 46539 | B17: =IF(ROW()-6<=参数设置!$B$6,ROW()-6,"") -> 11 | C17: =IF(B17="","",EDATE(参数设置!$B$4,B17-1)) -> 46548 | D17: =IF(B17="",0,参数设置!$B$5) -> 23400 | E17: =参数设置!$B$7 -> 0.92 | F17: =IF(D17=0,0,D17/E17) -> 25434.783 | G17: =F17*参数设置!$B$21 -> 0 | H17: =F17-G17 -> 25434.783 | I17: =IF(ROW()=7,H17,I16+H17) -> 279782.61 | J17: =I17*参数设置!$B$17/参数设置!$B$18 -> 1165.7609 | K17: =IF(ROW()=7,0,J16) -> 1059.7826 | L17: =IF(ROW()=7,K17,L16+K17) -> 5828.8043 | M17: =SUMIFS(贷款明细!$H$4:$H$435,贷款明细!$F$4:$F$435,">="&A17,贷款明细!$F$4:$F$435,"<"&EDATE(A17,1)) -> 0 | N17: =SUMIFS(贷款明细!$I$4:$I$435,贷款明细!$F$4:$F$435,">="&A17,贷款明细!$F$4:$F$435,"<"&EDATE(A17,1)) -> 652.12 | O17: =M17+N17 -> 652.12 | P17: =O17/E17 -> 708.82609 | Q17: =-H17+K17-P17 -> -25083.826 | R17: =M17 -> 0 | S17: =SUM($D$7:D17)-SUM($M$7:M17) -> 257400 | T17: =S17/E17 -> 279782.61 | U17: =I17+L17 -> 285611.41 | V17: =U17-T17-SUM($N$7:N17)/E17 -> 2114.5652
A18: =EDATE(DATE(YEAR(参数设置!$B$4),MONTH(参数设置!$B$4),1),ROW()-7) -> 46569 | B18: =IF(ROW()-6<=参数设置!$B$6,ROW()-6,"") -> 12 | C18: =IF(B18="","",EDATE(参数设置!$B$4,B18-1)) -> 46578 | D18: =IF(B18="",0,参数设置!$B$5) -> 23400 | E18: =参数设置!$B$7 -> 0.92 | F18: =IF(D18=0,0,D18/E18) -> 25434.783 | G18: =F18*参数设置!$B$21 -> 0 | H18: =F18-G18 -> 25434.783 | I18: =IF(ROW()=7,H18,I17+H18) -> 305217.39 | J18: =I18*参数设置!$B$17/参数设置!$B$18 -> 1271.7391 | K18: =IF(ROW()=7,0,J17) -> 1165.7609 | L18: =IF(ROW()=7,K18,L17+K18) -> 6994.5652 | M18: =SUMIFS(贷款明细!$H$4:$H$435,贷款明细!$F$4:$F$435,">="&A18,贷款明细!$F$4:$F$435,"<"&EDATE(A18,1)) -> 0 | N18: =SUMIFS(贷款明细!$I$4:$I$435,贷款明细!$F$4:$F$435,">="&A18,贷款明细!$F$4:$F$435,"<"&EDATE(A18,1)) -> 699.27 | O18: =M18+N18 -> 699.27 | P18: =O18/E18 -> 760.07609 | Q18: =-H18+K18-P18 -> -25029.098 | R18: =M18 -> 0 | S18: =SUM($D$7:D18)-SUM($M$7:M18) -> 280800 | T18: =S18/E18 -> 305217.39 | U18: =I18+L18 -> 312211.96 | V18: =U18-T18-SUM($N$7:N18)/E18 -> 2520.25
... A54: =EDATE(DATE(YEAR(参数设置!$B$4),MONTH(参数设置!$B$4),1),ROW()-7) -> 47665 | B54: =IF(ROW()-6<=参数设置!$B$6,ROW()-6,"") | C54: =IF(B54="","",EDATE(参数设置!$B$4,B54-1)) | D54: =IF(B54="",0,参数设置!$B$5) -> 0 | E54: =参数设置!$B$7 -> 0.92 | F54: =IF(D54=0,0,D54/E54) -> 0 | G54: =F54*参数设置!$B$21 -> 0 | H54: =F54-G54 -> 0 | I54: =IF(ROW()=7,H54,I53+H54) -> 610434.78 | J54: =I54*参数设置!$B$17/参数设置!$B$18 -> 2543.4783 | K54: =IF(ROW()=7,0,J53) -> 2543.4783 | L54: =IF(ROW()=7,K54,L53+K54) -> 90293.478 | M54: =SUMIFS(贷款明细!$H$4:$H$435,贷款明细!$F$4:$F$435,">="&A54,贷款明细!$F$4:$F$435,"<"&EDATE(A54,1)) -> 23400 | N54: =SUMIFS(贷款明细!$I$4:$I$435,贷款明细!$F$4:$F$435,">="&A54,贷款明细!$F$4:$F$435,"<"&EDATE(A54,1)) -> 0 | O54: =M54+N54 -> 23400 | P54: =O54/E54 -> 25434.783 | Q54: =-H54+K54-P54 -> -22891.304 | R54: =M54 -> 23400 | S54: =SUM($D$7:D54)-SUM($M$7:M54) -> -280800 | T54: =S54/E54 -> -305217.39 | U54: =I54+L54 -> 700728.26 | V54: =U54-T54-SUM($N$7:N54)/E54 -> 985492.57
A55: 累计/期末 | D55: =SUM(D7:D54) -> 561600 | F55: =SUM(F7:F54) -> 610434.78 | G55: =SUM(G7:G54) -> 0 | H55: =SUM(H7:H54) -> 610434.78 | I55: =I54 -> 610434.78 | J55: =SUM(J7:J54) -> 92836.957 | K55: =SUM(K7:K54) -> 90293.478 | L55: =L54 -> 90293.478 | M55: =SUM(M7:M54) -> 842400 | N55: =SUM(N7:N54) -> 18816.84 | O55: =SUM(O7:O54) -> 861216.84 | P55: =SUM(P7:P54) -> 936105.26 | Q55: =SUM(Q7:Q54) -> -1456246.6 | R55: =R54 -> 23400 | S55: =S54 -> -280800 | T55: =T54 -> -305217.39 | U55: =U54 -> 700728.26 | V55: =V54 -> 985492.57

Sheet 贷款明细
A1: 贷款明细（每笔贷款逐期计息）
A3: 贷款批次 | B3: 放款日 | C3: 贷款本金（人民币） | D3: 期数 | E3: 本期起始日 | F3: 本期还款日 | G3: 计息天数 | H3: 当期本金（人民币） | I3: 当期利息（人民币） | J3: 当期还款（人民币） | K3: 本金到期日 | L3: 是否启用
A4: 1 | B4: =EDATE(参数设置!$B$4,A4-1) -> 46244 | C4: =参数设置!$B$5 -> 23400 | D4: 1 | E4: =IF(D4=1,B4,F3) -> 46244 | F4: =IF(D4<参数设置!$B$12,DATE(YEAR(EDATE(B4,D4+1)),MONTH(EDATE(B4,D4+1)),参数设置!$B$13),EDATE(B4,参数设置!$B$12)) -> 46300 | G4: =F4-E4 -> 56 | H4: =IF(D4=参数设置!$B$12,C4,0) -> 0 | I4: =IF(L4=1,ROUND(C4*参数设置!$B$10*G4/参数设置!$B$11,参数设置!$B$14),0) -> 120.12 | J4: =H4+I4 -> 120.12 | K4: =EDATE(B4,参数设置!$B$12) -> 46609 | L4: =--(A4<=参数设置!$B$6) -> 1
A5: 1 | B5: =EDATE(参数设置!$B$4,A5-1) -> 46244 | C5: =参数设置!$B$5 -> 23400 | D5: 2 | E5: =IF(D5=1,B5,F4) -> 46300 | F5: =IF(D5<参数设置!$B$12,DATE(YEAR(EDATE(B5,D5+1)),MONTH(EDATE(B5,D5+1)),参数设置!$B$13),EDATE(B5,参数设置!$B$12)) -> 46331 | G5: =F5-E5 -> 31 | H5: =IF(D5=参数设置!$B$12,C5,0) -> 0 | I5: =IF(L5=1,ROUND(C5*参数设置!$B$10*G5/参数设置!$B$11,参数设置!$B$14),0) -> 66.5 | J5: =H5+I5 -> 66.5 | K5: =EDATE(B5,参数设置!$B$12) -> 46609 | L5: =--(A5<=参数设置!$B$6) -> 1
A6: 1 | B6: =EDATE(参数设置!$B$4,A6-1) -> 46244 | C6: =参数设置!$B$5 -> 23400 | D6: 3 | E6: =IF(D6=1,B6,F5) -> 46331 | F6: =IF(D6<参数设置!$B$12,DATE(YEAR(EDATE(B6,D6+1)),MONTH(EDATE(B6,D6+1)),参数设置!$B$13),EDATE(B6,参数设置!$B$12)) -> 46361 | G6: =F6-E6 -> 30 | H6: =IF(D6=参数设置!$B$12,C6,0) -> 0 | I6: =IF(L6=1,ROUND(C6*参数设置!$B$10*G6/参数设置!$B$11,参数设置!$B$14),0) -> 64.35 | J6: =H6+I6 -> 64.35 | K6: =EDATE(B6,参数设置!$B$12) -> 46609 | L6: =--(A6<=参数设置!$B$6) -> 1
A7: 1 | B7: =EDATE(参数设置!$B$4,A7-1) -> 46244 | C7: =参数设置!$B$5 -> 23400 | D7: 4 | E7: =IF(D7=1,B7,F6) -> 46361 | F7: =IF(D7<参数设置!$B$12,DATE(YEAR(EDATE(B7,D7+1)),MONTH(EDATE(B7,D7+1)),参数设置!$B$13),EDATE(B7,参数设置!$B$12)) -> 46392 | G7: =F7-E7 -> 31 | H7: =IF(D7=参数设置!$B$12,C7,0) -> 0 | I7: =IF(L7=1,ROUND(C7*参数设置!$B$10*G7/参数设置!$B$11,参数设置!$B$14),0) -> 66.5 | J7: =H7+I7 -> 66.5 | K7: =EDATE(B7,参数设置!$B$12) -> 46609 | L7: =--(A7<=参数设置!$B$6) -> 1
A8: 1 | B8: =EDATE(参数设置!$B$4,A8-1) -> 46244 | C8: =参数设置!$B$5 -> 23400 | D8: 5 | E8: =IF(D8=1,B8,F7) -> 46392 | F8: =IF(D8<参数设置!$B$12,DATE(YEAR(EDATE(B8,D8+1)),MONTH(EDATE(B8,D8+1)),参数设置!$B$13),EDATE(B8,参数设置!$B$12)) -> 46423 | G8: =F8-E8 -> 31 | H8: =IF(D8=参数设置!$B$12,C8,0) -> 0 | I8: =IF(L8=1,ROUND(C8*参数设置!$B$10*G8/参数设置!$B$11,参数设置!$B$14),0) -> 66.5 | J8: =H8+I8 -> 66.5 | K8: =EDATE(B8,参数设置!$B$12) -> 46609 | L8: =--(A8<=参数设置!$B$6) -> 1
A9: 1 | B9: =EDATE(参数设置!$B$4,A9-1) -> 46244 | C9: =参数设置!$B$5 -> 23400 | D9: 6 | E9: =IF(D9=1,B9,F8) -> 46423 | F9: =IF(D9<参数设置!$B$12,DATE(YEAR(EDATE(B9,D9+1)),MONTH(EDATE(B9,D9+1)),参数设置!$B$13),EDATE(B9,参数设置!$B$12)) -> 46451 | G9: =F9-E9 -> 28 | H9: =IF(D9=参数设置!$B$12,C9,0) -> 0 | I9: =IF(L9=1,ROUND(C9*参数设置!$B$10*G9/参数设置!$B$11,参数设置!$B$14),0) -> 60.06 | J9: =H9+I9 -> 60.06 | K9: =EDATE(B9,参数设置!$B$12) -> 46609 | L9: =--(A9<=参数设置!$B$6) -> 1
A10: 1 | B10: =EDATE(参数设置!$B$4,A10-1) -> 46244 | C10: =参数设置!$B$5 -> 23400 | D10: 7 | E10: =IF(D10=1,B10,F9) -> 46451 | F10: =IF(D10<参数设置!$B$12,DATE(YEAR(EDATE(B10,D10+1)),MONTH(EDATE(B10,D10+1)),参数设置!$B$13),EDATE(B10,参数设置!$B$12)) -> 46482 | G10: =F10-E10 -> 31 | H10: =IF(D10=参数设置!$B$12,C10,0) -> 0 | I10: =IF(L10=1,ROUND(C10*参数设置!$B$10*G10/参数设置!$B$11,参数设置!$B$14),0) -> 66.5 | J10: =H10+I10 -> 66.5 | K10: =EDATE(B10,参数设置!$B$12) -> 46609 | L10: =--(A10<=参数设置!$B$6) -> 1
A11: 1 | B11: =EDATE(参数设置!$B$4,A11-1) -> 46244 | C11: =参数设置!$B$5 -> 23400 | D11: 8 | E11: =IF(D11=1,B11,F10) -> 46482 | F11: =IF(D11<参数设置!$B$12,DATE(YEAR(EDATE(B11,D11+1)),MONTH(EDATE(B11,D11+1)),参数设置!$B$13),EDATE(B11,参数设置!$B$12)) -> 46512 | G11: =F11-E11 -> 30 | H11: =IF(D11=参数设置!$B$12,C11,0) -> 0 | I11: =IF(L11=1,ROUND(C11*参数设置!$B$10*G11/参数设置!$B$11,参数设置!$B$14),0) -> 64.35 | J11: =H11+I11 -> 64.35 | K11: =EDATE(B11,参数设置!$B$12) -> 46609 | L11: =--(A11<=参数设置!$B$6) -> 1
A12: 1 | B12: =EDATE(参数设置!$B$4,A12-1) -> 46244 | C12: =参数设置!$B$5 -> 23400 | D12: 9 | E12: =IF(D12=1,B12,F11) -> 46512 | F12: =IF(D12<参数设置!$B$12,DATE(YEAR(EDATE(B12,D12+1)),MONTH(EDATE(B12,D12+1)),参数设置!$B$13),EDATE(B12,参数设置!$B$12)) -> 46543 | G12: =F12-E12 -> 31 | H12: =IF(D12=参数设置!$B$12,C12,0) -> 0 | I12: =IF(L12=1,ROUND(C12*参数设置!$B$10*G12/参数设置!$B$11,参数设置!$B$14),0) -> 66.5 | J12: =H12+I12 -> 66.5 | K12: =EDATE(B12,参数设置!$B$12) -> 46609 | L12: =--(A12<=参数设置!$B$6) -> 1
A13: 1 | B13: =EDATE(参数设置!$B$4,A13-1) -> 46244 | C13: =参数设置!$B$5 -> 23400 | D13: 10 | E13: =IF(D13=1,B13,F12) -> 46543 | F13: =IF(D13<参数设置!$B$12,DATE(YEAR(EDATE(B13,D13+1)),MONTH(EDATE(B13,D13+1)),参数设置!$B$13),EDATE(B13,参数设置!$B$12)) -> 46573 | G13: =F13-E13 -> 30 | H13: =IF(D13=参数设置!$B$12,C13,0) -> 0 | I13: =IF(L13=1,ROUND(C13*参数设置!$B$10*G13/参数设置!$B$11,参数设置!$B$14),0) -> 64.35 | J13: =H13+I13 -> 64.35 | K13: =EDATE(B13,参数设置!$B$12) -> 46609 | L13: =--(A13<=参数设置!$B$6) -> 1
A14: 1 | B14: =EDATE(参数设置!$B$4,A14-1) -> 46244 | C14: =参数设置!$B$5 -> 23400 | D14: 11 | E14: =IF(D14=1,B14,F13) -> 46573 | F14: =IF(D14<参数设置!$B$12,DATE(YEAR(EDATE(B14,D14+1)),MONTH(EDATE(B14,D14+1)),参数设置!$B$13),EDATE(B14,参数设置!$B$12)) -> 46604 | G14: =F14-E14 -> 31 | H14: =IF(D14=参数设置!$B$12,C14,0) -> 0 | I14: =IF(L14=1,ROUND(C14*参数设置!$B$10*G14/参数设置!$B$11,参数设置!$B$14),0) -> 66.5 | J14: =H14+I14 -> 66.5 | K14: =EDATE(B14,参数设置!$B$12) -> 46609 | L14: =--(A14<=参数设置!$B$6) -> 1
A15: 1 | B15: =EDATE(参数设置!$B$4,A15-1) -> 46244 | C15: =参数设置!$B$5 -> 23400 | D15: 12 | E15: =IF(D15=1,B15,F14) -> 46604 | F15: =IF(D15<参数设置!$B$12,DATE(YEAR(EDATE(B15,D15+1)),MONTH(EDATE(B15,D15+1)),参数设置!$B$13),EDATE(B15,参数设置!$B$12)) -> 46609 | G15: =F15-E15 -> 5 | H15: =IF(D15=参数设置!$B$12,C15,0) -> 23400 | I15: =IF(L15=1,ROUND(C15*参数设置!$B$10*G15/参数设置!$B$11,参数设置!$B$14),0) -> 10.73 | J15: =H15+I15 -> 23410.73 | K15: =EDATE(B15,参数设置!$B$12) -> 46609 | L15: =--(A15<=参数设置!$B$6) -> 1
... A435: 36 | B435: =EDATE(参数设置!$B$4,A435-1) -> 47309 | C435: =参数设置!$B$5 -> 23400 | D435: 12 | E435: =IF(D435=1,B435,F434) -> 47669 | F435: =IF(D435<参数设置!$B$12,DATE(YEAR(EDATE(B435,D435+1)),MONTH(EDATE(B435,D435+1)),参数设置!$B$13),EDATE(B435,参数设置!$B$12)) -> 47674 | G435: =F435-E435 -> 5 | H435: =IF(D435=参数设置!$B$12,C435,0) -> 23400 | I435: =IF(L435=1,ROUND(C435*参数设置!$B$10*G435/参数设置!$B$11,参数设置!$B$14),0) -> 0 | J435: =H435+I435 -> 23400 | K435: =EDATE(B435,参数设置!$B$12) -> 47674 | L435: =--(A435<=参数设置!$B$6) -> 0
